{
  "schemaVersion": 1,
  "lastUpdated": ["2026-07-14"],
  "source": "manual",
  "prices": [
    { "code": "GOL", "name": "Garanti", "rate": -0.7814 },
    { "code": "YKT", "name": "Yapı Kredi", "rate": -0.7946 },
    { "code": "GTA", "name": "Garanti", "rate": -0.9025 },
    { "code": "TCA", "name": "Ziraat", "rate": -1.0376 },
    { "code": "KMN", "name": "Yapı Kredi", "rate": -1.1147 },
    { "code": "VK6", "name": "V", "rate": 0.1173 },
    { "code": "ENR", "name": "QNB", "rate": 0.1145 },
    { "code": "GTL", "name": "Garanti", "rate": 0.1138 },
    { "code": "YLB", "name": "Yapı Kredi", "rate": 0.1125 },
    { "code": "TI1", "name": "İş", "rate": 0.1077 },
    { "code": "TZL", "name": "Ziraat", "rate": 0.1072 },
    { "code": "ALE", "name": "Ak", "rate": 0.1069 },
    { "code": "TKM", "name": "TEB", "rate": 0.1055 },
    { "code": "AN1", "name": "Strateji", "rate": 1.4947 },
    { "code": "YAE", "name": "Yapı Kredi", "rate": 0.1055 },
    { "code": "SKO", "name": "Strateji", "rate": -0.8057 },
    { "code": "YZC", "name": "Yapı Kredi", "rate": -1.0078 },
    { "code": "YAY", "name": "Yapı Kredi", "rate": -2.0097 },
    { "code": "PPS", "name": "Phillip", "rate": 3.8075 },
    { "code": "BSM", "name": "Global MD", "rate": 0.4133 },
    { "code": "GZM", "name": "Global MD", "rate": 0.3868 },
    { "code": "SKZ", "name": "Neo", "rate": 0.2794 },
    { "code": "TLY", "name": "Tera", "rate": 0.1235 },
    { "code": "RTP", "name": "Re-Pie", "rate": -0.3731 },
    { "code": "MOZ", "name": "Emaa Blue", "rate": -0.5524 },
    { "code": "FBV", "name": "İş", "rate": -0.6889 },
    { "code": "ODP", "name": "Osmanlı", "rate": -0.8859 },
    { "code": "TGE", "name": "İş", "rate": 0.5603 },
    { "code": "RGD", "name": "Re-Pie", "rate": 0.2225 },
    { "code": "ICH", "name": "Pardus", "rate": 0.1919 },
    { "code": "BVD", "name": "BV", "rate": 0.1023 },
    { "code": "MD1", "name": "MT", "rate": -0.0205 },
    { "code": "EVM", "name": "Deniz", "rate": -0.0953 },
    { "code": "BHF", "name": "Pardus", "rate": -0.2599 },
    { "code": "RIK", "name": "Re-Pie", "rate": -0.5126 },
    { "code": "IPB", "name": "İstanbul", "rate": -0.5913 },
    { "code": "CPU", "name": "Aktif", "rate": -0.7408 },
    { "code": "IED", "name": "İş", "rate": -0.7507 },
    { "code": "HIZ", "name": "Azimut", "rate": -0.9342 },
    { "code": "EBD", "name": "Global MD", "rate": -1.1861 },
    { "code": "RTG", "name": "Ata", "rate": -1.2468 },
    { "code": "MTD", "name": "BV", "rate": -1.2933 },
    { "code": "URA", "name": "Ata", "rate": -1.5405 },
    { "code": "YZT", "name": "Ak", "rate": -1.6236 },
    { "code": "NTI", "name": "Neo", "rate": -1.8384 },
    { "code": "IJC", "name": "İş", "rate": -2.1726 },
    { "code": "NMU", "name": "Nurol", "rate": 0.6748 },
    { "code": "LPH", "name": "Statech", "rate": 0.2855 },
    { "code": "BHI", "name": "BV", "rate": 0.2639 },
    { "code": "PPM", "name": "Piramit", "rate": 0.2456 },
    { "code": "IRB", "name": "İstanbul", "rate": 0.1559 },
    { "code": "NSH", "name": "Nurol", "rate": -0.1909 },
    { "code": "TP2", "name": "Tera", "rate": 0.1279 },
    { "code": "MT2", "name": "MT", "rate": 0.1276 },
    { "code": "MPL", "name": "MT", "rate": 0.1231 },
    { "code": "FSF", "name": "Fiba", "rate": 0.1201 },
    { "code": "PPN", "name": "Nurol", "rate": 0.1152 },
    { "code": "DLY", "name": "Deniz", "rate": 0.1122 },
    { "code": "PPJ", "name": "Ak", "rate": 0.1102 },
    { "code": "BGP", "name": "Ak", "rate": 0.1089 },
    { "code": "DCB", "name": "Deniz", "rate": 0.1087 },
    { "code": "PTE", "name": "TEB", "rate": 0.1078 },
    { "code": "AIS", "name": "Ak", "rate": 0.1077 },
    { "code": "FSK", "name": "QNB", "rate": 0.107 },
    { "code": "NSP", "name": "Nurol", "rate": 0.1069 },
    { "code": "TLV", "name": "Tera", "rate": 0.1059 },
    { "code": "FIL", "name": "Fiba", "rate": 0.1052 },
    { "code": "TRJ", "name": "Tera", "rate": 0.3131 },
    { "code": "MBR", "name": "MT", "rate": 0.1741 },
    { "code": "BBF", "name": "Pardus", "rate": 0.1307 },
    { "code": "NJR", "name": "Nurol", "rate": 0.1133 },
    { "code": "TFU", "name": "İş", "rate": 0.0739 },
    { "code": "MHF", "name": "MT", "rate": 1.0323 },
    { "code": "PTO", "name": "Pardus", "rate": 0.5988 },
    { "code": "KHA", "name": "Pardus", "rate": 0.337 },
    { "code": "BIY", "name": "Azimut", "rate": 0.159 },
    { "code": "GLG", "name": "Aktif", "rate": -0.1461 },
    { "code": "NLE", "name": "Nurol", "rate": -0.3338 },
    { "code": "HRZ", "name": "Aktif", "rate": -0.3562 },
    { "code": "BDS", "name": "Pardus", "rate": -0.4115 },
    { "code": "MTH", "name": "MT", "rate": -0.4433 },
    { "code": "MLT", "name": "Deniz", "rate": -0.5023 },
    { "code": "NUH", "name": "Neo", "rate": -0.5985 },
    { "code": "PPH", "name": "Pardus", "rate": -0.6299 },
    { "code": "RHI", "name": "Re-Pie", "rate": -0.7961 },
    { "code": "RTH", "name": "Re-Pie", "rate": -0.8458 },
    { "code": "NPH", "name": "Nurol", "rate": -0.9268 },
    { "code": "BV1", "name": "BV", "rate": -0.9603 },
    { "code": "DOH", "name": "Tera", "rate": -1.0993 },
    { "code": "ONE", "name": "Aktif", "rate": -1.2396 },
    { "code": "THF", "name": "Tera", "rate": -1.3676 },
    { "code": "RIH", "name": "Re-Pie", "rate": -9.8179 },
    { "code": "TMG", "name": "İş", "rate": 0.2694 },
    { "code": "AFA", "name": "Ak", "rate": 0.1761 },
    { "code": "AFV", "name": "Ak", "rate": -0.1022 },
    { "code": "AFT", "name": "Ak", "rate": -1.128 },
    { "code": "GMI", "name": "Ak", "rate": 0.2011 },
    { "code": "FMG", "name": "QNB", "rate": -0.677 },
    { "code": "FPG", "name": "Fiba", "rate": -1.4884 },
    { "code": "IOG", "name": "İş", "rate": -1.8404 },
    { "code": "TMV", "name": "Tera", "rate": 1.9 }
  ]
}
